btc2sim/__init__.py
btc2sim/atomics.py
btc2sim/bank.py
btc2sim/bt.py
btc2sim/classes.py
btc2sim/dsl.py
btc2sim/info.py
btc2sim/utils.py
btc2sim-0.0.6.dist-info/METADATA
btc2sim-0.0.6.dist-info/WHEEL
btc2sim-0.0.6.dist-info/RECORD
