Metadata-Version: 2.1
Name: btc2sim
Version: 0.0.6
Summary: 
Author: Noah Syrkis
Author-email: noah@syrkis.com
Requires-Python: >=3.11,<3.12
Classifier: Programming Language :: Python :: 3
Classifier: Programming Language :: Python :: 3.11
Requires-Dist: einops (>=0.8.0,<0.9.0)
Requires-Dist: functional (>=0.4,<0.5)
Requires-Dist: ipykernel (>=6.29.5,<7.0.0)
Requires-Dist: jupyterlab (>=4.2.4,<5.0.0)
Requires-Dist: lark (>=1.1.9,<2.0.0)
Requires-Dist: notebook (>=7.2.1,<8.0.0)
Requires-Dist: parabellum (>=0.3.4)
Requires-Dist: tqdm (>=4.66.5,<5.0.0)
